pystructui/__init__.py
pystructui/core.py
pystructui/integrations.py
pystructui/renderers.py
pystructui-0.1.0.dist-info/licenses/LICENSE
pystructui-0.1.0.dist-info/METADATA
pystructui-0.1.0.dist-info/WHEEL
pystructui-0.1.0.dist-info/entry_points.txt
pystructui-0.1.0.dist-info/top_level.txt
pystructui-0.1.0.dist-info/RECORD
